LICENSE
MANIFEST.in
README.rst
conf.json.example
setup.py
doc/api.rst
src/dipus/__init__.py
src/dipus/config.py
src/dipus/dipusbuilder.py
src/dipus/docstore.py
src/dipus/search_html_t.py
src/dipus/search_js_t.py
src/dipus/websetup.py
src/dipus.egg-info/PKG-INFO
src/dipus.egg-info/SOURCES.txt
src/dipus.egg-info/dependency_links.txt
src/dipus.egg-info/requires.txt
src/dipus.egg-info/top_level.txt
src/dipus/_static/css/bootstrap-responsive.css
src/dipus/_static/css/bootstrap-responsive.min.css
src/dipus/_static/css/bootstrap.css
src/dipus/_static/css/bootstrap.css~
src/dipus/_static/css/bootstrap.min.css
src/dipus/_static/css/dipus.css
src/dipus/_static/css/dipus.css~
src/dipus/_static/img/glyphicons-halflings-white.png
src/dipus/_static/img/glyphicons-halflings.png
src/dipus/_static/js/bootstrap.js
src/dipus/_static/js/bootstrap.min.js
src/dipus/_static/js/jquery-1.8.1.min.js
src/dipus/_static/js/search_dipus.js
src/dipus/_static/js/search_dipus.js~
src/dipus/_templates/index.html~
src/dipus/_templates/index.tpl
test/rst/Makefile
test/rst/README.rst
test/rst/conf.py
test/rst/index.rst
test/rst/test-1.rst
test/rst/_static/search_dipus.js
test/rst/_templates/search_dipus.html
test/rst/dir/index.rst
test/rst/dir/test-1.rst
test/rst/dir/test2.rst