Metadata-Version: 1.1
Name: dipus
Version: 0.0.5
Summary: Dipus is a simple full-text search server using Whoosh for Sphinx
Home-page: http://bitbucket.org/r_rudi/dipus
Author: WAKAYAMA shirou
Author-email: shirou.faw at gmail.com
License: BSD License
Keywords: sphinx,whoosh,text search
Platform: UNKNOWN
Classifier: Development Status :: 3 - Alpha
Classifier: License :: OSI Approved :: BSD License
Classifier: Programming Language :: Python :: 2.7
Classifier: Topic :: Database :: Database Engines/Servers
Classifier: Topic :: Software Development :: Documentation
Classifier: Topic :: Documentation
